cli/__init__.py
cli/main.py
config/__init__.py
config/envs.py
config/logger.py
k8s/__init__.py
k8s/watcher.py
k8s/apps/__init__.py
k8s/apps/v1.py
k8s/core/__init__.py
k8s/core/v1.py
k8s/networking/__init__.py
k8s/networking/v1.py
salmorejo/__init__.py
salmorejo/__main__.py
salmorejo/service.py
salmorejo-0.2.0.dist-info/LICENSE
salmorejo-0.2.0.dist-info/METADATA
salmorejo-0.2.0.dist-info/WHEEL
salmorejo-0.2.0.dist-info/entry_points.txt
salmorejo-0.2.0.dist-info/top_level.txt
salmorejo-0.2.0.dist-info/RECORD
