Metadata-Version: 2.1
Name: salmorejo
Version: 0.2.0
Summary: Tool for testing and debugging Kubernetes events/changes in real time
Author-email: Gonzalo Gabriel Jiménez Fuentes <iam@mendrugory.com>
License: The MIT License (MIT)
Project-URL: Homepage, https://github.com/mendrugory/salmorejo
Keywords: salmorejo,kubernetes,watcher
Classifier: License :: OSI Approved :: MIT License
Classifier: Programming Language :: Python
Classifier: Programming Language :: Python :: 3
Requires-Python: >=3.8
License-File: LICENSE
Requires-Dist: click (==8.1.3)
Requires-Dist: kubernetes (==24.2.0)
Provides-Extra: dev
Requires-Dist: beautifultable (==1.1.0) ; extra == 'dev'
